neurosym/__init__.py
neurosym/__main__.py
neurosym/cli_tui.py
neurosym/version.py
neurosym/engine/__init__.py
neurosym/engine/guard.py
neurosym/examples/00_smoke.py
neurosym/examples/01_pii_redaction.py
neurosym/examples/01_text_policy_smoke.py
neurosym/examples/02_invoice_json.py
neurosym/examples/02_text_policy_with_redaction.py
neurosym/examples/03_local_phi3.py
neurosym/examples/10_interactive_cli.py
neurosym/llm/__init__.py
neurosym/llm/base.py
neurosym/llm/fallback.py
neurosym/llm/gemini.py
neurosym/llm/ollama.py
neurosym/pre/redaction.py
neurosym/rules/__init__.py
neurosym/rules/base.py
neurosym/rules/policies.py
neurosym/rules/python_pred_rule.py
neurosym/rules/regex_rule.py
neurosym/rules/schema_rule.py
neurosym/schemas/invoice.json
neurosym/tests/test_guard.py
neurosym/tests/test_redaction_then_guard.py
neurosym/tests/test_rules_basic.py
neurosym/tests/test_text_policy.py
neurosym/utils/__init__.py
neurosym/utils/cli.py
neurosym/utils/json_tools.py
neurosym/utils/plugins.py
neurosym/utils/py.typed
neurosym_ai-0.1.3.dist-info/LICENSE
neurosym_ai-0.1.3.dist-info/METADATA
neurosym_ai-0.1.3.dist-info/WHEEL
neurosym_ai-0.1.3.dist-info/entry_points.txt
neurosym_ai-0.1.3.dist-info/top_level.txt
neurosym_ai-0.1.3.dist-info/RECORD
