Metadata-Version: 2.2
Name: neurosym-ai
Version: 0.1.3
Summary: Neuro-symbolic guardrails for LLMs: rules + repair loops + (optional) SMT.
Author: Aadit Pani
License:                                  Apache License
Project-URL: Homepage, https://github.com/AaditPani-RVU/NeuroSym-AI
Project-URL: Repository, https://github.com/AaditPani-RVU/NeuroSym-AI
Project-URL: Issues, https://github.com/AaditPani-RVU/NeuroSym-AI/issues
Keywords: llm,guardrails,neurosymbolic,safety,policy,rules
Classifier: Programming Language :: Python :: 3
Classifier: Programming Language :: Python :: 3 :: Only
Classifier: Operating System :: OS Independent
Requires-Python: >=3.10
License-File: LICENSE
Requires-Dist: jsonschema>=4.23
Requires-Dist: httpx>=0.27
Requires-Dist: tenacity>=9.0
Requires-Dist: rich>=13.7
Requires-Dist: typer>=0.12
Requires-Dist: typing-extensions>=4.7.0; python_version < "3.11"
Provides-Extra: z3
Requires-Dist: z3-solver>=4.12; extra == "z3"
Provides-Extra: providers
Requires-Dist: google-generativeai>=0.7.2; extra == "providers"
Requires-Dist: requests>=2.31.0; extra == "providers"
Provides-Extra: dev
Requires-Dist: pytest>=8.0; extra == "dev"
Requires-Dist: pytest-cov>=5.0; extra == "dev"
Requires-Dist: mypy>=1.10; extra == "dev"
Requires-Dist: ruff>=0.6.0; extra == "dev"
Requires-Dist: pre-commit>=3.5.0; extra == "dev"
Requires-Dist: build; extra == "dev"
Requires-Dist: twine; extra == "dev"
Requires-Dist: python-dotenv>=1.0; extra == "dev"
